iso_mcp_server/__init__.py
iso_mcp_server/reporting.py
iso_mcp_server/rules_loader.py
iso_mcp_server/server.py
iso_mcp_server/tooling.py
iso_mcp_server-0.1.2.dist-info/METADATA
iso_mcp_server-0.1.2.dist-info/WHEEL
iso_mcp_server-0.1.2.dist-info/entry_points.txt
iso_mcp_server-0.1.2.dist-info/top_level.txt
iso_mcp_server-0.1.2.dist-info/RECORD
