Metadata-Version: 2.4
Name: iso-mcp-server
Version: 0.1.2
Summary: MCP server exposing tools to validate ISO 45001/9001 MoM spreadsheets
Author-email: Your Name <you@example.com>
Requires-Python: >=3.10
Requires-Dist: pandas>=2.1.0
Requires-Dist: openpyxl>=3.1.2
Requires-Dist: python-docx>=1.1.0
Requires-Dist: markdown>=3.5.1
Requires-Dist: jinja2>=3.1.3
Requires-Dist: mcp>=1.0.0
Requires-Dist: uvicorn>=0.30.0
Requires-Dist: fastapi>=0.111.0
